{"version": 0.6, "generator": "Overpass API 0.7.62.11 87bfad18", "osm3s": {"timestamp_osm_base": "2026-06-04T14:40:00Z", "copyright": "The data included in this document is from www.openstreetmap.org. The data is made available under ODbL."}, "elements": [{"type": "node", "id": 60168789, "lat": 46.2296157, "lon": 7.8833886, "tags": {"is_in": "Bezirk Visp,Valais;Wallis,Valais,Schweiz,Europe", "name": "Staldenried", "openGeoDB:auto_update": "population,is_in", "openGeoDB:community_identification_number": "G6294", "openGeoDB:is_in": "Bezirk Visp,Valais;Wallis,Valais,Schweiz,Europe", "openGeoDB:is_in_loc_id": "78686", "openGeoDB:layer": "6", "openGeoDB:loc_id": "32160", "openGeoDB:name": "Staldenried", "openGeoDB:population": "554", "openGeoDB:postal_codes": "3933", "openGeoDB:sort_name": "STALDENRIED", "openGeoDB:type": "Gemeinde", "openGeoDB:version": "0.2.6.11 / 2007-12-04 / http://fa-technik.adfc.de/code/opengeodb/dump/", "opengeodb:lat": "46.2284671", "opengeodb:lon": "7.886112", "place": "village", "population": "554"}}, {"type": "node", "id": 80387968, "lat": 46.0212076, "lon": 7.749254, "tags": {"ele": "1608", "is_in": "Wallis", "name": "Zermatt", "name:ja": "\u30c4\u30a7\u30eb\u30de\u30c3\u30c8", "old_name:fr": "Praborgne", "openGeoDB:auto_update": "population", "openGeoDB:community_identification_number": "G6300", "openGeoDB:is_in": "Bezirk Visp,Valais;Wallis,Valais,Schweiz,Europe", "openGeoDB:is_in_loc_id": "78686", "openGeoDB:layer": "6", "openGeoDB:loc_id": "32184", "openGeoDB:name": "Zermatt", "openGeoDB:population": "5786", "openGeoDB:postal_codes": "3920", "openGeoDB:sort_name": "ZERMATT", "openGeoDB:type": "Gemeinde", "openGeoDB:version": "0.2.6.11 / 2007-12-04 / http://fa-technik.adfc.de/code/opengeodb/dump/", "opengeodb:lat": "46.0221644", "opengeodb:lon": "7.7496219", "place": "town", "population": "5786", "website": "https://www.zermatt.ch/", "wikidata": "Q27494", "wikipedia": "de:Zermatt"}}, {"type": "node", "id": 197501928, "lat": 46.2311749, "lon": 7.3588795, "tags": {"admin_centre:4": "yes", "ele": "515", "name": "Sion", "name:be": "\u0421\u044c\u0451\u043d", "name:de": "Sitten", "name:fr": "Sion", "name:ko": "\uc2dc\uc639", "name:lt": "Sionas", "name:ru": "\u0421\u044c\u043e\u043d", "name:uk": "\u0421\u044c\u0439\u043e\u043d", "note": "deutscher Name gem\u00e4ss Kantonsverfassung", "openGeoDB:community_identification_number": "G6266", "openGeoDB:is_in": "District de Sion,Valais;Wallis,Valais,Schweiz,Europe", "openGeoDB:loc_id": "32159", "openGeoDB:postal_codes": "1950, 1951, 1992", "place": "town", "population": "34599", "postal_code": "1950, 1951, 1992", "website": "https://www.sion.ch/", "wikidata": "Q68136", "wikipedia": "fr:Sion (Valais)"}}, {"type": "node", "id": 240027151, "lat": 46.1733718, "lon": 7.4421788, "tags": {"ele": "1411", "is_in": "District d'H\u00e9rens,Valais;Wallis,Valais,Schweiz,Europe", "name": "St-Martin VS", "official_name": "Saint-Martin (VS)", "openGeoDB:auto_update": "population,place,name,is_in", "openGeoDB:community_identification_number": "G6087", "openGeoDB:is_in": "District d'H\u00e9rens,Valais;Wallis,Valais,Schweiz,Europe", "openGeoDB:is_in_loc_id": "78678", "openGeoDB:layer": "6", "openGeoDB:license_plate_code": "VS", "openGeoDB:loc_id": "79876", "openGeoDB:location": "political_structure", "openGeoDB:name": "Saint-Martin (VS)", "openGeoDB:population": "897", "openGeoDB:postal_codes": "1969", "openGeoDB:sort_name": "SAINT-MARTIN", "openGeoDB:type": "Gemeinde", "openGeoDB:version": "0.2.6.11 / 2007-12-04 / http://fa-technik.adfc.de/code/opengeodb/dump/", "place": "village", "population": "897"}}, {"type": "node", "id": 240031311, "lat": 46.1370186, "lon": 7.7925667, "tags": {"is_in": "Sankt Niklaus,Bezirk Visp,Valais;Wallis,Valais,Schweiz,Europe", "name": "Herbriggen", "openGeoDB:auto_update": "population,place,name,is_in", "openGeoDB:is_in": "Sankt Niklaus,Bezirk Visp,Valais;Wallis,Valais,Schweiz,Europe", "openGeoDB:is_in_loc_id": "79911", "openGeoDB:layer": "7", "openGeoDB:loc_id": "32108", "openGeoDB:location": "locality", "openGeoDB:name": "Herbriggen", "openGeoDB:postal_codes": "3927", "openGeoDB:sort_name": "HERBRIGGEN", "openGeoDB:version": "0.2.6.11 / 2007-12-04 / http://fa-technik.adfc.de/code/opengeodb/dump/", "place": "village"}}, {"type": "node", "id": 240035309, "lat": 46.177002, "lon": 7.802516, "tags": {"alt_name": "St. Niklaus", "name": "Sankt Niklaus", "name:ru": "\u0421\u0430\u043d\u043a\u0442-\u041d\u0438\u043a\u043b\u0430\u0443\u0441", "name:uk": "\u0421\u0430\u043d\u043a\u0442-\u041d\u0456\u043a\u043b\u0430\u0443\u0441", "place": "village", "population": "2268", "population:date": "2023-12-31", "source:population": "wikipedia", "wikidata": "Q68464"}}, {"type": "node", "id": 240040129, "lat": 46.2081821, "lon": 7.3752716, "tags": {"ele": "1002", "is_in": "District d'H\u00e9rens,Valais;Wallis,Valais,Schweiz,Europe", "name": "Les Agettes", "place": "village", "population": "347", "postal_code": "1992", "website": "https://www.sion.ch/", "wikidata": "Q70365", "wikipedia": "fr:Les Agettes"}}, {"type": "node", "id": 240043267, "lat": 46.2205594, "lon": 7.596488, "tags": {"ele": "1655", "is_in": "District de Sierre,Valais;Wallis,Valais,Schweiz,Europe", "name": "Saint-Luc", "openGeoDB:auto_update": "population,place,name,is_in", "openGeoDB:community_identification_number": "G6247", "openGeoDB:is_in": "District de Sierre,Valais;Wallis,Valais,Schweiz,Europe", "openGeoDB:is_in_loc_id": "78684", "openGeoDB:layer": "6", "openGeoDB:license_plate_code": "VS", "openGeoDB:loc_id": "79903", "openGeoDB:location": "political_structure", "openGeoDB:name": "Saint-Luc", "openGeoDB:population": "319", "openGeoDB:postal_codes": "3961", "openGeoDB:sort_name": "SAINT-LUC", "openGeoDB:type": "Gemeinde", "openGeoDB:version": "0.2.6.11 / 2007-12-04 / http://fa-technik.adfc.de/code/opengeodb/dump/", "place": "village", "population": "319", "wikidata": "Q689586"}}, {"type": "node", "id": 240047919, "lat": 46.2112722, "lon": 7.7069255, "tags": {"is_in": "Ergisch,Bezirk Leuk,Valais;Wallis,Valais,Schweiz,Europe", "name": "Gruben", "openGeoDB:auto_update": "population,place,name,is_in", "openGeoDB:is_in": "Ergisch,Bezirk Leuk,Valais;Wallis,Valais,Schweiz,Europe", "openGeoDB:is_in_loc_id": "79877", "openGeoDB:layer": "7", "openGeoDB:loc_id": "32107", "openGeoDB:location": "locality", "openGeoDB:name": "Gruben", "openGeoDB:postal_codes": "3946", "openGeoDB:sort_name": "GRUBEN", "openGeoDB:version": "0.2.6.11 / 2007-12-04 / http://fa-technik.adfc.de/code/opengeodb/dump/", "place": "village"}}, {"type": "node", "id": 240051216, "lat": 46.1960178, "lon": 7.8421612, "tags": {"name": "Gr\u00e4chen", "place": "village", "population": "1254"}}, {"type": "node", "id": 240062204, "lat": 46.1720564, "lon": 7.4235858, "tags": {"is_in": "H\u00e9r\u00e9mence,H\u00e9r\u00e9mence,District d'H\u00e9rens,Valais;Wallis,Valais,Schweiz,Europe", "name": "Euseigne", "openGeoDB:postal_codes": "1982", "place": "village", "postal_code": "1982", "wikidata": "Q971334"}}, {"type": "node", "id": 240071397, "lat": 46.2325963, "lon": 7.8704203, "tags": {"is_in": "Bezirk Visp,Valais;Wallis,Valais,Schweiz,Europe", "name": "Stalden VS", "openGeoDB:auto_update": "population,place,name,is_in", "openGeoDB:community_identification_number": "G6293", "openGeoDB:is_in": "Bezirk Visp,Valais;Wallis,Valais,Schweiz,Europe", "openGeoDB:is_in_loc_id": "78686", "openGeoDB:layer": "6", "openGeoDB:license_plate_code": "VS", "openGeoDB:loc_id": "79912", "openGeoDB:location": "political_structure", "openGeoDB:name": "Stalden (VS)", "openGeoDB:population": "1149", "openGeoDB:postal_codes": "3922", "openGeoDB:sort_name": "STALDEN", "openGeoDB:type": "Gemeinde", "openGeoDB:version": "0.2.6.11 / 2007-12-04 / http://fa-technik.adfc.de/code/opengeodb/dump/", "place": "village", "population": "1149", "url": "http://www.stalden.ch/", "wikidata": "Q68460"}}, {"type": "node", "id": 240083548, "lat": 46.1988458, "lon": 7.8949076, "tags": {"created_by": "opengeodb2osm0.5.2", "is_in": "Bezirk Visp,Valais;Wallis,Valais,Schweiz,Europe", "name": "Eisten", "openGeoDB:auto_update": "population,place,name,is_in", "openGeoDB:community_identification_number": "G6282", "openGeoDB:is_in": "Bezirk Visp,Valais;Wallis,Valais,Schweiz,Europe", "openGeoDB:is_in_loc_id": "78686", "openGeoDB:layer": "6", "openGeoDB:loc_id": "32079", "openGeoDB:location": "political_structure", "openGeoDB:name": "Eisten", "openGeoDB:population": "226", "openGeoDB:postal_codes": "3922,3909", "openGeoDB:sort_name": "EISTEN", "openGeoDB:type": "Gemeinde", "openGeoDB:version": "0.2.6.11 / 2007-12-04 / http://fa-technik.adfc.de/code/opengeodb/dump/", "place": "village", "population": "226", "wikidata": "Q67088"}}, {"type": "node", "id": 240085078, "lat": 46.2153165, "lon": 7.5853597, "tags": {"ele": "1204", "is_in": "District de Sierre,Valais;Wallis,Valais,Schweiz,Europe", "name": "Vissoie", "openGeoDB:auto_update": "population,place,name,is_in", "openGeoDB:community_identification_number": "G6251", "openGeoDB:is_in": "District de Sierre,Valais;Wallis,Valais,Schweiz,Europe", "openGeoDB:is_in_loc_id": "78684", "openGeoDB:layer": "6", "openGeoDB:loc_id": "32181", "openGeoDB:location": "political_structure", "openGeoDB:name": "Vissoie,Vissoie", "openGeoDB:population": "451", "openGeoDB:postal_codes": "3961", "openGeoDB:sort_name": "VISSOIE", "openGeoDB:type": "Gemeinde", "openGeoDB:version": "0.2.6.11 / 2007-12-04 / http://fa-technik.adfc.de/code/opengeodb/dump/", "place": "village", "population": "451", "wikidata": "Q689112"}}, {"type": "node", "id": 240091775, "lat": 46.2109663, "lon": 7.4313684, "tags": {"is_in": "District d'H\u00e9rens,Valais;Wallis,Valais,Schweiz,Europe", "name": "Vernami\u00e8ge", "openGeoDB:auto_update": "population,place,name,is_in", "openGeoDB:community_identification_number": "G6088", "openGeoDB:is_in": "District d'H\u00e9rens,Valais;Wallis,Valais,Schweiz,Europe", "openGeoDB:is_in_loc_id": "78678", "openGeoDB:layer": "6", "openGeoDB:loc_id": "32173", "openGeoDB:location": "political_structure", "openGeoDB:name": "Vernami\u00e8ge,Vernami\u00e8ge", "openGeoDB:population": "144", "openGeoDB:postal_codes": "1961", "openGeoDB:sort_name": "VERNAMIEGE", "openGeoDB:type": "Gemeinde", "openGeoDB:version": "0.2.6.11 / 2007-12-04 / http://fa-technik.adfc.de/code/opengeodb/dump/", "place": "village", "population": "160", "postal_code": "1961", "wikidata": "Q664221"}}, {"type": "node", "id": 240099788, "lat": 46.2385196, "lon": 7.851508, "tags": {"ele": "1497", "name": "T\u00f6rbel", "name:uk": "\u0422\u043e\u0440\u0431\u0435\u043b\u044c", "place": "village", "population": "494", "population:date": "2023-12-31", "source:population": "wikipedia", "wikidata": "Q68469"}}, {"type": "node", "id": 240100166, "lat": 46.2110679, "lon": 7.35707, "tags": {"ele": "842", "is_in": "District de Sion,Valais;Wallis,Valais,Schweiz,Europe", "name": "Salins", "openGeoDB:auto_update": "population,place,name,is_in", "openGeoDB:community_identification_number": "G6264", "openGeoDB:is_in": "District de Sion,Valais;Wallis,Valais,Schweiz,Europe", "openGeoDB:is_in_loc_id": "78685", "openGeoDB:layer": "6", "openGeoDB:license_plate_code": "VS", "openGeoDB:loc_id": "79906", "openGeoDB:location": "political_structure", "openGeoDB:name": "Salins", "openGeoDB:population": "960", "openGeoDB:postal_codes": "1991", "openGeoDB:sort_name": "SALINS", "openGeoDB:type": "Gemeinde", "openGeoDB:version": "0.2.6.11 / 2007-12-04 / http://fa-technik.adfc.de/code/opengeodb/dump/", "place": "village", "population": "960", "postal_code": "1991", "wikidata": "Q689668", "wikipedia": "fr:Salins (Valais)"}}, {"type": "node", "id": 240112350, "lat": 46.1960916, "lon": 7.5855687, "tags": {"is_in": "District de Sierre,Valais;Wallis,Valais,Schweiz,Europe", "name": "St-Jean VS", "openGeoDB:auto_update": "population,place,name,is_in", "openGeoDB:community_identification_number": "G6245", "openGeoDB:is_in": "District de Sierre,Valais;Wallis,Valais,Schweiz,Europe", "openGeoDB:is_in_loc_id": "78684", "openGeoDB:layer": "6", "openGeoDB:license_plate_code": "VS", "openGeoDB:loc_id": "79901", "openGeoDB:location": "political_structure", "openGeoDB:name": "Saint-Jean", "openGeoDB:population": "196", "openGeoDB:postal_codes": "3961", "openGeoDB:sort_name": "SAINT-JEAN", "openGeoDB:type": "Gemeinde", "openGeoDB:version": "0.2.6.11 / 2007-12-04 / http://fa-technik.adfc.de/code/opengeodb/dump/", "place": "village", "population": "196", "wikidata": "Q15881638"}}, {"type": "node", "id": 240123898, "lat": 46.0676751, "lon": 7.7770173, "tags": {"ele": "1449", "is_in": "Bezirk Visp,Valais;Wallis,Valais,Schweiz,Europe", "name": "T\u00e4sch", "openGeoDB:auto_update": "population,place,name,is_in", "openGeoDB:community_identification_number": "G6295", "openGeoDB:is_in": "Bezirk Visp,Valais;Wallis,Valais,Schweiz,Europe", "openGeoDB:is_in_loc_id": "78686", "openGeoDB:layer": "6", "openGeoDB:loc_id": "32163", "openGeoDB:location": "political_structure", "openGeoDB:name": "T\u00e4sch", "openGeoDB:population": "1235", "openGeoDB:postal_codes": "3929", "openGeoDB:sort_name": "TAESCH", "openGeoDB:type": "Gemeinde", "openGeoDB:version": "0.2.6.11 / 2007-12-04 / http://fa-technik.adfc.de/code/opengeodb/dump/", "place": "village", "population": "1235", "postal_code": "3929", "website": "https://www.gemeinde-taesch.ch/", "wikidata": "Q69305", "wikipedia": "de:T\u00e4sch"}}, {"type": "node", "id": 240125755, "lat": 46.1002792, "lon": 7.782412, "tags": {"is_in": "Bezirk Visp,Valais;Wallis,Valais,Schweiz,Europe", "name": "Randa", "name:uk": "\u0420\u0430\u043d\u0434\u0430", "openGeoDB:auto_update": "population,place,name,is_in", "openGeoDB:community_identification_number": "G6287", "openGeoDB:is_in": "Bezirk Visp,Valais;Wallis,Valais,Schweiz,Europe", "openGeoDB:is_in_loc_id": "78686", "openGeoDB:layer": "6", "openGeoDB:loc_id": "32144", "openGeoDB:location": "political_structure", "openGeoDB:name": "Randa", "openGeoDB:population": "404", "openGeoDB:postal_codes": "3928", "openGeoDB:sort_name": "RANDA", "openGeoDB:type": "Gemeinde", "openGeoDB:version": "0.2.6.11 / 2007-12-04 / http://fa-technik.adfc.de/code/opengeodb/dump/", "place": "village", "population": "461", "population:date": "2023-12-31", "source:population": "wikipedia", "website": "https://www.randa.ch/", "wikidata": "Q67720", "wikipedia": "de:Randa VS"}}, {"type": "node", "id": 240129045, "lat": 46.2589888, "lon": 7.9030118, "tags": {"ele": "1391", "name": "Visperterminen", "place": "village", "population": "1357"}}, {"type": "node", "id": 251402040, "lat": 46.1804744, "lon": 7.8261138, "tags": {"name": "Gasenried", "place": "village", "wikidata": "Q1495092", "wikipedia": "de:Gasenried"}}, {"type": "node", "id": 253338916, "lat": 45.9356034, "lon": 7.6304397, "tags": {"alt_name": "Cervinia", "ele": "2050", "loc_name": "Breuil", "name": "Breuil-Cervinia", "place": "village", "population": "700", "wikidata": "Q911159", "wikipedia": "it:Breuil-Cervinia"}}, {"type": "node", "id": 281283143, "lat": 46.1802947, "lon": 7.573834, "tags": {"ele": "1564", "name": "Grimentz", "place": "village", "postal_code": "3961", "wikidata": "Q869551"}}, {"type": "node", "id": 281290328, "lat": 46.2102226, "lon": 7.5830688, "tags": {"name": "Mayoux", "place": "village", "wikidata": "Q3303024"}}, {"type": "node", "id": 283573856, "lat": 46.1946906, "lon": 7.4313991, "tags": {"ele": "1345", "name": "Mase", "place": "village", "postal_code": "1968", "wikidata": "Q662273", "wikipedia": "fr:Mase"}}, {"type": "node", "id": 283573950, "lat": 46.2113825, "lon": 7.3983622, "tags": {"is_in": "Valais, Suisse", "name": "Vex", "name:uk": "\u0412\u0435", "place": "village", "population": "1929", "population:date": "2023-12-31", "postal_code": "1981", "source:population": "wikipedia", "wikidata": "Q67724"}}, {"type": "node", "id": 283614851, "lat": 46.1807413, "lon": 7.4057866, "tags": {"is_in": "Valais, suisse", "name": "H\u00e9r\u00e9mence", "name:frp": "H\u00e8rmence", "place": "village", "population": "0", "postal_code": "1987", "wikidata": "Q69553"}}, {"type": "node", "id": 283615244, "lat": 46.1803848, "lon": 7.4372006, "tags": {"is_in": "Saint-Martin, Valais, Suisse", "name": "Suen (St-Martin)", "place": "village", "postal_code": "1969"}}, {"type": "node", "id": 283616160, "lat": 46.2321819, "lon": 7.4038983, "tags": {"is_in": "Sion, Valais, Suisse", "name": "Bramois", "name:de": "Br\u00e4mis", "place": "village", "postal_code": "1967", "wikidata": "Q1652215"}}, {"type": "node", "id": 286501533, "lat": 46.1619787, "lon": 7.4512969, "tags": {"name": "Liez (St-Martin)", "openGeoDB:license_plate_code": "VS", "place": "hamlet"}}, {"type": "node", "id": 286501854, "lat": 46.1399405, "lon": 7.4678912, "tags": {"name": "La Villette", "openGeoDB:license_plate_code": "VS", "place": "hamlet"}}, {"type": "node", "id": 286502727, "lat": 46.1523819, "lon": 7.4536008, "tags": {"name": "Praz-Jean", "openGeoDB:license_plate_code": "VS", "place": "hamlet"}}, {"type": "node", "id": 286503178, "lat": 46.1129048, "lon": 7.4958022, "tags": {"ele": "1371", "is_in": "Valais, suisse", "name": "Evol\u00e8ne", "name:ko": "\ub9c8\uc744", "place": "village", "postal_code": "1983", "wikidata": "Q69551"}}, {"type": "node", "id": 286503828, "lat": 46.159282, "lon": 7.4414903, "tags": {"name": "La Luette", "openGeoDB:license_plate_code": "VS", "place": "hamlet"}}, {"type": "node", "id": 291050527, "lat": 46.1544699, "lon": 7.4662005, "tags": {"ele": "1662", "name": "Eison (St-Martin)", "place": "village"}}, {"type": "node", "id": 291050648, "lat": 46.0987565, "lon": 7.5146993, "tags": {"name": "La Sage", "place": "village", "wikidata": "Q17347100"}}, {"type": "node", "id": 291050651, "lat": 46.085784, "lon": 7.5191144, "tags": {"name": "La Forclaz VS", "place": "village", "population": "130"}}, {"type": "node", "id": 291050660, "lat": 46.0827039, "lon": 7.5075706, "tags": {"ele": "1454", "name": "Les Haud\u00e8res", "place": "village", "wikidata": "Q1820530"}}, {"type": "node", "id": 291050663, "lat": 46.1686148, "lon": 7.4513221, "tags": {"ele": "1478", "name": "Trogne (St-Martin)", "place": "village"}}, {"type": "node", "id": 291052554, "lat": 46.0659514, "lon": 7.5437277, "tags": {"name": "Ferp\u00e8cle (Le Salay)", "place": "hamlet"}}, {"type": "node", "id": 292896518, "lat": 46.2062861, "lon": 7.3958926, "tags": {"name": "Les Prasses", "place": "hamlet"}}, {"type": "node", "id": 295427978, "lat": 46.2452766, "lon": 7.4742488, "tags": {"name": "Loye", "place": "village"}}, {"type": "node", "id": 295428291, "lat": 46.2424693, "lon": 7.46322, "tags": {"name": "Daillet", "place": "village"}}, {"type": "node", "id": 297023039, "lat": 46.1656564, "lon": 7.3966238, "tags": {"name": "Prolin", "place": "village"}}, {"type": "node", "id": 297023047, "lat": 46.1205671, "lon": 7.4791099, "tags": {"name": "Lanna", "place": "hamlet"}}, {"type": "node", "id": 297023164, "lat": 46.1619758, "lon": 7.3954851, "tags": {"name": "Cerise", "place": "village"}}, {"type": "node", "id": 297024725, "lat": 46.1614359, "lon": 7.3897798, "tags": {"name": "Riod", "place": "village"}}, {"type": "node", "id": 297025427, "lat": 46.0975019, "lon": 7.5058976, "tags": {"name": "La Tour VS", "place": "hamlet"}}, {"type": "node", "id": 299759888, "lat": 46.225128, "lon": 7.9027064, "tags": {"name": "Gspon", "place": "village", "wikidata": "Q1552506"}}, {"type": "node", "id": 308504436, "lat": 46.136287, "lon": 7.6267982, "tags": {"ele": "1675", "name": "Zinal", "place": "village", "postal_code": "3961", "wikidata": "Q204247"}}, {"type": "node", "id": 321868912, "lat": 46.1797895, "lon": 7.3961464, "tags": {"name": "Les Masses", "place": "hamlet", "wikidata": "Q3100977"}}, {"type": "node", "id": 364691620, "lat": 46.1590707, "lon": 7.7952807}, {"type": "node", "id": 364691621, "lat": 46.1591191, "lon": 7.7951911}, {"type": "node", "id": 384792978, "lat": 46.2127182, "lon": 7.5779647, "tags": {"name": "Les Frasses", "place": "hamlet"}}, {"type": "node", "id": 384800463, "lat": 46.251007, "lon": 7.4582384, "tags": {"ele": "513", "name": "Gr\u00f4ne", "name:fr": "Gr\u00f4ne", "old_name:de": "Gr\u00fcn", "place": "village", "population": "2311", "postal_code": "3979", "website": "https://www.grone.ch/", "wikidata": "Q70151", "wikipedia": "fr:Gr\u00f4ne"}}, {"type": "node", "id": 436369768, "lat": 46.2470228, "lon": 7.8637948, "tags": {"name": "Burgen", "place": "hamlet"}}, {"type": "node", "id": 440896495, "lat": 46.1123018, "lon": 7.3972338, "tags": {"name": "Pralong", "place": "hamlet"}}, {"type": "node", "id": 459832275, "lat": 46.0068723, "lon": 7.6946031, "tags": {"name": "Biel", "place": "hamlet"}}, {"type": "node", "id": 459834520, "lat": 46.0019602, "lon": 7.7301989, "tags": {"name": "Furi", "place": "hamlet", "wikidata": "Q1474937", "wikipedia": "de:Furi"}}, {"type": "node", "id": 560700324, "lat": 46.1810491, "lon": 7.3717832, "tags": {"ele": "2095", "name": "Thyon", "place": "hamlet"}}, {"type": "node", "id": 600048453, "lat": 46.025975, "lon": 7.4810866, "tags": {"ele": "2006", "name": "Arolla", "place": "village", "wikidata": "Q691979"}}, {"type": "node", "id": 600498919, "lat": 46.0398377, "lon": 7.488854, "tags": {"alt_name": "Pramo\u00fbss", "name": "Pramousse", "place": "hamlet"}}, {"type": "node", "id": 600513328, "lat": 46.0536064, "lon": 7.4897397, "tags": {"name": "La Gouille", "place": "hamlet"}}, {"type": "node", "id": 600513368, "lat": 46.0471766, "lon": 7.4881295, "tags": {"name": "Satarma", "place": "hamlet"}}, {"type": "node", "id": 600514761, "lat": 46.0237038, "lon": 7.4822933, "tags": {"name": "Mont-Collon", "place": "hamlet"}}, {"type": "node", "id": 682201392, "lat": 46.0064782, "lon": 7.7170895, "tags": {"name": "Zmutt", "place": "hamlet", "wikidata": "Q217946"}}, {"type": "node", "id": 707822199, "lat": 46.2207331, "lon": 7.570188, "tags": {"is_in": "District de Sierre", "name": "Pinsec", "place": "hamlet"}}, {"type": "node", "id": 804764993, "lat": 46.0592709, "lon": 7.8109743, "tags": {"ele": "2205", "name": "Ottafe", "place": "hamlet"}}, {"type": "node", "id": 853324212, "lat": 46.2137891, "lon": 7.8376939, "tags": {"name": "Kalpetran", "place": "village"}}, {"type": "node", "id": 853493745, "lat": 46.1915035, "lon": 7.8285991, "tags": {"name": "Niedergr\u00e4chen", "place": "hamlet"}}, {"type": "node", "id": 855031999, "lat": 46.2267697, "lon": 7.4250269, "tags": {"ele": "1265", "name": "Nax", "place": "village", "postal_code": "1973", "wikidata": "Q689087"}}, {"type": "node", "id": 891281661, "lat": 46.2303693, "lon": 7.8765662, "tags": {"is_in": "Staldenried", "name": "Furrershaus", "place": "hamlet"}}, {"type": "node", "id": 891281664, "lat": 46.2334014, "lon": 7.876482, "tags": {"name": "Niederried", "place": "hamlet"}}, {"type": "node", "id": 891281684, "lat": 46.2268018, "lon": 7.8814322, "tags": {"is_in": "Staldenried", "name": "Lochstadel", "place": "hamlet"}}, {"type": "node", "id": 891281701, "lat": 46.2302991, "lon": 7.8868761, "tags": {"is_in": "Staldenried", "name": "Brunnmatte", "place": "hamlet"}}, {"type": "node", "id": 992849683, "lat": 46.2535137, "lon": 7.7768022, "tags": {"ele": "1990", "is_in": "Unterb\u00e4ch", "name": "Unners S\u00e4nntum", "place": "hamlet"}}, {"type": "node", "id": 1016532223, "lat": 46.160238, "lon": 7.7965039}, {"type": "node", "id": 1016532278, "lat": 46.1603108, "lon": 7.795835}, {"type": "node", "id": 1129573061, "lat": 46.2214778, "lon": 7.8908884, "tags": {"name": "Sengge", "place": "hamlet"}}, {"type": "node", "id": 1129584951, "lat": 46.2294511, "lon": 7.890886, "tags": {"name": "Zer Flie", "place": "hamlet"}}, {"type": "node", "id": 1129645132, "lat": 46.2234777, "lon": 7.9026546, "tags": {"name": "Ze Hischinu", "place": "hamlet"}}, {"type": "node", "id": 1143955997, "lat": 46.2299021, "lon": 7.8792191, "tags": {"is_in": "Staldenried", "name": "Bord", "place": "hamlet"}}, {"type": "node", "id": 1163297002, "lat": 46.2145659, "lon": 7.8547227, "tags": {"name": "Bargji", "place": "hamlet"}}, {"type": "node", "id": 1181099737, "lat": 46.191154, "lon": 7.4730904, "tags": {"name": "L'Arpette", "place": "hamlet"}}, {"type": "node", "id": 1264721133, "lat": 45.9137553, "lon": 7.619754, "tags": {"name": "Alpe Promindoz-Desot", "place": "hamlet"}}, {"type": "node", "id": 1264721284, "lat": 45.9100302, "lon": 7.6226399, "tags": {"name": "Alpe Promindoz-Damon", "place": "hamlet"}}, {"type": "node", "id": 1264721314, "lat": 45.8983389, "lon": 7.6387018, "tags": {"name": "Alpe Molar", "place": "hamlet"}}, {"type": "node", "id": 1264721330, "lat": 45.9118998, "lon": 7.6209237, "tags": {"name": "Alpe Promindoz-Di-Meiten", "place": "hamlet"}}, {"type": "node", "id": 1264721356, "lat": 45.9090086, "lon": 7.6177581, "tags": {"name": "Alpe Perreres", "place": "hamlet"}}, {"type": "node", "id": 1287766352, "lat": 45.9073806, "lon": 7.6139457, "tags": {"name": "Varvoies", "place": "hamlet"}}, {"type": "node", "id": 1287766585, "lat": 45.9083343, "lon": 7.6159671, "tags": {"alt_name": "Perr\u00e8res", "name": "Les Perr\u00e8res", "place": "hamlet", "wikidata": "Q18495603"}}, {"type": "node", "id": 1287766705, "lat": 45.8974145, "lon": 7.608363, "tags": {"name": "Tza Grillon", "place": "hamlet"}}, {"type": "node", "id": 1293128575, "lat": 46.2427743, "lon": 7.7725043, "tags": {"name": "Obers S\u00e4nntum", "place": "hamlet"}}, {"type": "node", "id": 1312041795, "lat": 46.1823389, "lon": 7.8120572, "tags": {"ele": "1200", "highway": "bus_stop", "name": "St. Niklaus, Wichel", "operator": "MGB", "public_transport": "platform", "shelter": "no", "uic_name": "St. Niklaus VS, Wichel", "uic_ref": "8501724"}}, {"type": "node", "id": 1352606782, "lat": 45.8965121, "lon": 7.4788679, "tags": {"alt_name": "La Leitzie", "ele": "1812", "name": "La L\u00e9ch\u00e8re", "place": "hamlet"}}, {"type": "node", "id": 1352606850, "lat": 45.8943313, "lon": 7.4543634, "tags": {"name": "Grand Chamin", "place": "hamlet"}}, {"type": "node", "id": 1353509417, "lat": 45.8829755, "lon": 7.4526796, "tags": {"ele": "1622", "name": "Pouillayes", "place": "hamlet"}}, {"type": "node", "id": 1353685255, "lat": 45.9074682, "lon": 7.4999685, "tags": {"name": "Greysemma", "place": "hamlet"}}, {"type": "node", "id": 1362392722, "lat": 45.9022387, "lon": 7.4450182, "tags": {"name": "Les Crottes", "place": "hamlet"}}, {"type": "node", "id": 1362392813, "lat": 45.8965257, "lon": 7.4520467, "tags": {"name": "Plan Sec", "place": "hamlet"}}, {"type": "node", "id": 1384833231, "lat": 46.1604818, "lon": 7.797402}, {"type": "node", "id": 1384833234, "lat": 46.1604994, "lon": 7.7972284}, {"type": "node", "id": 1384833246, "lat": 46.160602, "lon": 7.7976306}, {"type": "node", "id": 1387773920, "lat": 46.2490187, "lon": 7.8596393, "tags": {"name": "Hostettu", "place": "hamlet"}}, {"type": "node", "id": 1388884438, "lat": 46.1544451, "lon": 7.4955741, "tags": {"ele": "2370", "name": "L'a Vieille", "place": "hamlet"}}, {"type": "node", "id": 1388884446, "lat": 46.1952393, "lon": 7.4771385, "tags": {"name": "La Lou\u00e8re", "place": "hamlet"}}, {"type": "node", "id": 1388884448, "lat": 46.1742977, "lon": 7.4696146, "tags": {"name": "Lov\u00e9gno", "place": "hamlet"}}, {"type": "node", "id": 1388884454, "lat": 46.1530211, "lon": 7.5075383, "tags": {"name": "Plan Levri", "place": "hamlet"}}, {"type": "node", "id": 1411123346, "lat": 45.8966315, "lon": 7.4748446, "tags": {"name": "Pralet", "place": "hamlet"}}, {"type": "node", "id": 1436350146, "lat": 46.1787664, "lon": 7.6032682, "tags": {"ele": "1476", "name": "Ayer", "place": "village", "postal_code": "3961", "wikidata": "Q212308"}}, {"type": "node", "id": 1436350147, "lat": 46.2525826, "lon": 7.5986698, "tags": {"ele": "1920", "name": "Chandolin", "place": "village", "postal_code": "3961", "wikidata": "Q586631"}}, {"type": "node", "id": 1517506913, "lat": 45.896277, "lon": 7.5393386, "tags": {"name": "Chardoney", "place": "hamlet"}}, {"type": "node", "id": 1517506918, "lat": 45.916348, "lon": 7.5282851, "tags": {"alt_name": "Plan de l'Arpe", "name": "Pian dell'Arp", "place": "hamlet"}}, {"type": "node", "id": 1519126716, "lat": 45.9189057, "lon": 7.5252417, "tags": {"loc_name": "Ley", "name": "Les Ley", "place": "hamlet"}}, {"type": "node", "id": 1519126728, "lat": 45.9209054, "lon": 7.5250629, "tags": {"name": "Praz Mondzou Desot", "place": "hamlet"}}, {"type": "node", "id": 1519158931, "lat": 45.9208955, "lon": 7.5329017, "tags": {"ele": "2005", "name": "Prarayer", "place": "hamlet"}}, {"type": "node", "id": 1521095197, "lat": 45.9108545, "lon": 7.5053624, "tags": {"name": "Arpeyssaou", "place": "hamlet"}}, {"type": "node", "id": 1521167865, "lat": 45.9188812, "lon": 7.5198915, "tags": {"name": "Bas Oren", "place": "hamlet"}}, {"type": "node", "id": 1521167868, "lat": 45.928146, "lon": 7.5157322, "tags": {"name": "Garda", "place": "hamlet"}}, {"type": "node", "id": 1521167903, "lat": 45.9227678, "lon": 7.5207762, "tags": {"name": "Praz Mondzou Damon", "place": "hamlet"}}, {"type": "node", "id": 1523237069, "lat": 45.9101027, "lon": 7.489117, "tags": {"name": "Pian Vauon", "place": "hamlet"}}, {"type": "node", "id": 1523279256, "lat": 45.9038855, "lon": 7.4906635, "tags": {"name": "Le Me\u00e0", "place": "hamlet"}}, {"type": "node", "id": 1523279258, "lat": 45.9070959, "lon": 7.4926529, "tags": {"name": "Les Seytives", "place": "hamlet"}}, {"type": "node", "id": 1539960857, "lat": 46.1605127, "lon": 7.7977876}, {"type": "node", "id": 1539960869, "lat": 46.1592204, "lon": 7.7956381}, {"type": "node", "id": 1539960874, "lat": 46.1603975, "lon": 7.7978895}, {"type": "node", "id": 1539960875, "lat": 46.1594693, "lon": 7.7982191}, {"type": "node", "id": 1539960891, "lat": 46.1596766, "lon": 7.7981845}, {"type": "node", "id": 1539960944, "lat": 46.1593422, "lon": 7.7969561}, {"type": "node", "id": 1539960957, "lat": 46.1601485, "lon": 7.7980182}, {"type": "node", "id": 1539960982, "lat": 46.1594388, "lon": 7.7963016}, {"type": "node", "id": 1539960989, "lat": 46.1599449, "lon": 7.7981172}, {"type": "node", "id": 1539960994, "lat": 46.1591089, "lon": 7.7969907}, {"type": "node", "id": 1539961012, "lat": 46.1592687, "lon": 7.7960519}, {"type": "node", "id": 1539961019, "lat": 46.159042, "lon": 7.7972643}, {"type": "node", "id": 1539961028, "lat": 46.1593348, "lon": 7.7980826}, {"type": "node", "id": 1539961035, "lat": 46.1595317, "lon": 7.79672}, {"type": "node", "id": 1539961054, "lat": 46.1596105, "lon": 7.7964328}, {"type": "node", "id": 1539961060, "lat": 46.1594128, "lon": 7.7976481}, {"type": "node", "id": 1539961062, "lat": 46.1592085, "lon": 7.7953682}, {"type": "node", "id": 1539961063, "lat": 46.1591609, "lon": 7.7959339}, {"type": "node", "id": 1539961077, "lat": 46.1592085, "lon": 7.7973638}, {"type": "node", "id": 1676624678, "lat": 46.246295, "lon": 7.370919, "tags": {"name": "Champlan", "place": "hamlet", "postal_code": "1971", "website": "https://www.grimisuat.ch/"}}, {"type": "node", "id": 1707134693, "lat": 46.1828794, "lon": 7.4232116, "tags": {"alt_name": "Ossona", "name": "Ossone", "place": "hamlet"}}, {"type": "node", "id": 1754167433, "lat": 46.1557953, "lon": 7.3915601, "tags": {"is_in": "H\u00e9r\u00e9mence,District d'H\u00e9rens,Valais;Wallis,Valais,Schweiz,Europe", "name": "M\u00e2che", "place": "village"}}, {"type": "node", "id": 1764215405, "lat": 46.1813445, "lon": 7.3851407, "tags": {"name": "Les Collons", "place": "hamlet"}}, {"type": "node", "id": 1777747184, "lat": 45.9542941, "lon": 7.639639, "tags": {"name": "Mont de l'Eura", "place": "hamlet"}}, {"type": "node", "id": 1778184221, "lat": 45.9394349, "lon": 7.6322166, "tags": {"name": "Cr\u00e9taz", "place": "hamlet"}}, {"type": "node", "id": 1784397363, "lat": 45.9295705, "lon": 7.63112, "tags": {"addr:city": "Valtournenche", "name": "Cielo Alto", "place": "hamlet"}}, {"type": "node", "id": 1784739308, "lat": 45.9271658, "lon": 7.6184246, "tags": {"name": "Avuil", "place": "hamlet"}}, {"type": "node", "id": 1785651278, "lat": 45.9061776, "lon": 7.6182058, "tags": {"name": "Le Cr\u00eat", "place": "hamlet"}}, {"type": "node", "id": 1785651280, "lat": 45.9013554, "lon": 7.6275139, "tags": {"name": "Manda Desot", "place": "hamlet"}}, {"type": "node", "id": 1787876230, "lat": 45.9123775, "lon": 7.6095257, "tags": {"name": "Creton", "place": "hamlet"}}, {"type": "node", "id": 1836844439, "lat": 46.1774012, "lon": 7.4440868, "tags": {"name": "Baule", "place": "hamlet"}}, {"type": "node", "id": 1843731148, "lat": 46.2507131, "lon": 7.3502056, "tags": {"name": "Saint-Germain", "place": "village"}}, {"type": "node", "id": 1855394543, "lat": 45.9453565, "lon": 7.6311514, "tags": {"name": "Batse", "place": "hamlet"}}, {"type": "node", "id": 1871009955, "lat": 46.2272714, "lon": 7.8659799, "tags": {"name": "Illas", "place": "hamlet"}}, {"type": "node", "id": 2209091775, "lat": 46.1053183, "lon": 7.5135311, "tags": {"name": "Le Borza", "place": "hamlet"}}, {"type": "node", "id": 2209091785, "lat": 46.1067884, "lon": 7.5124009, "tags": {"ele": "1742", "name": "Villa (Evol\u00e8ne)", "note": "former Villaz", "old_name": "Villaz", "place": "village", "short_name": "Villa"}}, {"type": "node", "id": 2413457085, "lat": 46.1136449, "lon": 7.4766988, "tags": {"ele": "1750", "name": "Arbey", "place": "hamlet"}}, {"type": "node", "id": 2452315047, "lat": 46.2498087, "lon": 7.4164133, "tags": {"name": "Uvrier", "place": "village"}}, {"type": "node", "id": 2452315070, "lat": 46.2504276, "lon": 7.3923715, "tags": {"name": "Molignon", "place": "hamlet"}}, {"type": "node", "id": 2453978508, "lat": 45.8876487, "lon": 7.4579675, "tags": {"loc_name": "Chamein", "name": "Chamein", "place": "hamlet"}}, {"type": "node", "id": 2525093059, "lat": 46.0064949, "lon": 7.7320696, "tags": {"name": "Zum See", "place": "hamlet", "source": "visit", "wikidata": "Q16887824"}}, {"type": "node", "id": 2689726394, "lat": 46.2459226, "lon": 7.9101697, "tags": {"name": "Birch", "place": "hamlet"}}, {"type": "node", "id": 2921521063, "lat": 46.2520545, "lon": 7.3824828, "tags": {"name": "Les Fermes", "place": "hamlet"}}, {"type": "node", "id": 2925770313, "lat": 46.250656, "lon": 7.3731659, "tags": {"name": "Com\u00e9raz", "place": "hamlet"}}, {"type": "node", "id": 3072467880, "lat": 46.2231528, "lon": 7.8592532, "tags": {"name": "Liechtbiel", "place": "hamlet"}}, {"type": "node", "id": 3075889256, "lat": 46.1132564, "lon": 7.7943668, "tags": {"name": "Ch\u00fcebodmen", "place": "hamlet"}}, {"type": "node", "id": 3237934864, "lat": 46.2111142, "lon": 7.3847268, "tags": {"name": "Ypresse", "place": "hamlet"}}, {"type": "node", "id": 3238144941, "lat": 46.1899788, "lon": 7.5924995, "tags": {"name": "Mission", "place": "village", "wikidata": "Q794144"}}, {"type": "node", "id": 3238283782, "lat": 46.1567079, "lon": 7.6198685, "tags": {"name": "Mottec", "place": "hamlet"}}, {"type": "node", "id": 3272731172, "lat": 46.215848, "lon": 7.8283567, "tags": {"name": "Embd", "place": "village", "population": "353", "wikidata": "Q68026"}}, {"type": "node", "id": 3278345504, "lat": 46.2459867, "lon": 7.8598399, "tags": {"name": "Ze Springu", "place": "hamlet"}}, {"type": "node", "id": 3298159678, "lat": 46.1728314, "lon": 7.3940602, "tags": {"name": "Pachi\u00e8", "place": "hamlet"}}, {"type": "node", "id": 3351547296, "lat": 46.2316767, "lon": 7.8579084, "tags": {"name": "Brunnen", "place": "hamlet"}}, {"type": "node", "id": 3351549772, "lat": 46.2490965, "lon": 7.8674942, "tags": {"name": "Unnerflie", "place": "hamlet"}}, {"type": "node", "id": 3355835183, "lat": 46.2321908, "lon": 7.8507828, "tags": {"name": "Feld", "place": "hamlet"}}, {"type": "node", "id": 3393417072, "lat": 46.1441529, "lon": 7.6253716, "tags": {"name": "Le Bouillet", "place": "hamlet"}}, {"type": "node", "id": 3393417075, "lat": 46.1493089, "lon": 7.6240101, "tags": {"name": "Pralong", "place": "hamlet"}}, {"type": "node", "id": 3394164326, "lat": 46.2089085, "lon": 7.5907783, "tags": {"name": "La Combaz", "place": "hamlet"}}, {"type": "node", "id": 3394164327, "lat": 46.204557, "lon": 7.5909348, "tags": {"ele": "1280", "name": "Cuimey", "place": "hamlet"}}, {"type": "node", "id": 3394164776, "lat": 46.2111767, "lon": 7.5897967, "tags": {"name": "Les Morands", "place": "hamlet"}}, {"type": "node", "id": 3394967969, "lat": 46.2152383, "lon": 7.575024, "tags": {"name": "La Cretta", "place": "hamlet"}}, {"type": "node", "id": 3395077738, "lat": 46.2537384, "lon": 7.5714505, "tags": {"name": "Les Barmes", "place": "hamlet"}}, {"type": "node", "id": 3400248361, "lat": 46.0057678, "lon": 7.6898512, "tags": {"ele": "2139", "name": "Stafel", "place": "hamlet"}}, {"type": "node", "id": 3406298795, "lat": 46.0212659, "lon": 7.4807963, "tags": {"name": "Les Magines", "place": "hamlet"}}, {"type": "node", "id": 3406298797, "lat": 46.0298868, "lon": 7.487475, "tags": {"name": "Tsalion", "place": "hamlet"}}, {"type": "node", "id": 3406298798, "lat": 46.0320693, "lon": 7.486724, "tags": {"name": "La Monta", "place": "hamlet"}}, {"type": "node", "id": 3406298799, "lat": 46.0380054, "lon": 7.4864236, "tags": {"name": "Pra Grassette", "place": "hamlet"}}, {"type": "node", "id": 3406298800, "lat": 46.0388917, "lon": 7.4869708, "tags": {"name": "La L\u00e9", "place": "hamlet"}}, {"type": "node", "id": 3406298802, "lat": 46.0545872, "lon": 7.4881939, "tags": {"name": "Ouarts\u00e9", "place": "hamlet"}}, {"type": "node", "id": 3406298803, "lat": 46.0590544, "lon": 7.4904362, "tags": {"place": "hamlet"}}, {"type": "node", "id": 3406298807, "lat": 46.0782906, "lon": 7.5033644, "tags": {"name": "Pralovin", "place": "hamlet"}}, {"type": "node", "id": 3406332200, "lat": 46.0812992, "lon": 7.5246721, "tags": {"name": "La Tinde", "place": "hamlet"}}, {"type": "node", "id": 3406332204, "lat": 46.0872533, "lon": 7.5182053, "tags": {"name": "Place de Son La Forclaz", "place": "hamlet"}}, {"type": "node", "id": 3406659842, "lat": 46.0831546, "lon": 7.5001945, "tags": {"ele": "1560", "name": "Grand Boc", "place": "hamlet"}}, {"type": "node", "id": 3406659843, "lat": 46.0872623, "lon": 7.497523, "tags": {"name": "Farqu\u00e8ses", "place": "hamlet"}}, {"type": "node", "id": 3406659844, "lat": 46.085774, "lon": 7.5033381, "tags": {"name": "La Giette", "place": "hamlet"}}, {"type": "node", "id": 3406659845, "lat": 46.0907446, "lon": 7.4980273, "tags": {"name": "Grand Pra", "place": "hamlet"}}, {"type": "node", "id": 3406660862, "lat": 46.0958338, "lon": 7.4979629, "tags": {"alt_name": "L'Ata Gieute", "ele": "1770", "name": "La Giette", "place": "hamlet"}}, {"type": "node", "id": 3406660863, "lat": 46.0960793, "lon": 7.5034454, "tags": {"name": "Bevernec", "place": "hamlet"}}, {"type": "node", "id": 3406669439, "lat": 46.0898339, "lon": 7.5085623, "tags": {"name": "Molignon", "place": "hamlet"}}, {"type": "node", "id": 3406669442, "lat": 46.0921833, "lon": 7.5049885, "tags": {"name": "La Laveintse", "place": "hamlet"}}, {"type": "node", "id": 3406669443, "lat": 46.0934984, "lon": 7.5135931, "tags": {"name": "Les Coulayes", "place": "hamlet"}}, {"type": "node", "id": 3406669444, "lat": 46.0964075, "lon": 7.5162967, "tags": {"name": "Taillau", "place": "hamlet"}}, {"type": "node", "id": 3406669445, "lat": 46.095098, "lon": 7.5145801, "tags": {"name": "Plan de Bo\u00eb", "place": "hamlet"}}, {"type": "node", "id": 3406671998, "lat": 46.1004834, "lon": 7.5052862, "tags": {"name": "La Confraric", "place": "hamlet"}}, {"type": "node", "id": 3406678089, "lat": 46.1056893, "lon": 7.5011208, "tags": {"ele": "1386", "name": "La Fauch\u00e8re", "place": "hamlet"}}, {"type": "node", "id": 3406684363, "lat": 46.1097934, "lon": 7.5101169, "tags": {"name": "Pr\u00e9s de Villaz", "place": "hamlet"}}, {"type": "node", "id": 3429690440, "lat": 46.1381734, "lon": 7.631698, "tags": {"name": "Pralonzet", "place": "hamlet"}}, {"type": "node", "id": 3444468890, "lat": 46.0296258, "lon": 7.7739472, "tags": {"ele": "2215", "name": "Tufteren", "place": "hamlet"}}, {"type": "node", "id": 3444468891, "lat": 46.0132291, "lon": 7.7713419, "tags": {"ele": "2177", "name": "Eggen", "place": "hamlet"}}, {"type": "node", "id": 3444468892, "lat": 46.0110698, "lon": 7.7655124, "tags": {"ele": "2051", "name": "Ze Gassen", "place": "hamlet"}}, {"type": "node", "id": 3444469294, "lat": 46.0016666, "lon": 7.7505262, "tags": {"ele": "2222", "name": "Riffelalp", "place": "hamlet", "wikidata": "Q7333237", "wikipedia": "en:Riffelalp"}}, {"type": "node", "id": 3566091431, "lat": 46.2492032, "lon": 7.5862971, "tags": {"name": "La R\u00e8che", "place": "hamlet"}}, {"type": "node", "id": 3566091433, "lat": 46.2502885, "lon": 7.5969918, "tags": {"name": "Les Tisses", "place": "hamlet"}}, {"type": "node", "id": 3576493966, "lat": 46.2468245, "lon": 7.3481543, "tags": {"name": "Roumaz", "place": "village"}}, {"type": "node", "id": 3577413688, "lat": 46.2112046, "lon": 7.3463733, "tags": {"name": "Arvillard", "place": "hamlet"}}, {"type": "node", "id": 3577420006, "lat": 46.2155035, "lon": 7.3557962, "tags": {"name": "Turin", "place": "hamlet"}}, {"type": "node", "id": 3577421753, "lat": 46.2118585, "lon": 7.3539537, "tags": {"name": "Pravidondaz", "place": "hamlet"}}, {"type": "node", "id": 3602373594, "lat": 46.2105891, "lon": 7.3740439, "tags": {"name": "La Vernaz", "place": "hamlet"}}, {"type": "node", "id": 3602373595, "lat": 46.2115348, "lon": 7.3704076, "tags": {"alt_name": "Cr\u00eate \u00e0 l'Oeil", "name": "Cr\u00eate-\u00e0-l'Oeil", "place": "hamlet"}}, {"type": "node", "id": 3690068107, "lat": 46.2419039, "lon": 7.8744931, "tags": {"name": "Ackersand", "place": "hamlet"}}, {"type": "node", "id": 3690068109, "lat": 46.2486656, "lon": 7.8773807, "tags": {"name": "Milachru", "place": "hamlet"}}, {"type": "node", "id": 3690068110, "lat": 46.2520929, "lon": 7.8778122, "tags": {"name": "Neubr\u00fcck", "place": "hamlet"}}, {"type": "node", "id": 3946111109, "lat": 46.1840555, "lon": 7.7938768, "tags": {"name": "Sparren", "place": "hamlet"}}, {"type": "node", "id": 3981415419, "lat": 46.2400765, "lon": 7.8955523, "tags": {"name": "Riedji", "place": "hamlet"}}, {"type": "node", "id": 3981417218, "lat": 46.2541455, "lon": 7.8890813, "tags": {"name": "Ze Chalte Stadlu", "place": "hamlet"}}, {"type": "node", "id": 4058038687, "lat": 46.0076225, "lon": 7.7360406, "tags": {"name": "Blatten", "place": "hamlet", "source": "visit"}}, {"type": "node", "id": 4441268057, "lat": 46.2029648, "lon": 7.3716819, "tags": {"addr:city": "Les Mayens-de-Sion", "addr:postcode": "1992", "name": "Les Mayens de Sion", "place": "hamlet"}}, {"type": "node", "id": 4446384628, "lat": 46.196579, "lon": 7.4755646, "tags": {"name": "La Lou\u00e8re", "place": "hamlet"}}, {"type": "node", "id": 5514874040, "lat": 45.9249168, "lon": 7.5196328, "tags": {"name": "Grand Oren", "place": "hamlet"}}, {"type": "node", "id": 5779462319, "lat": 45.9372665, "lon": 7.641192, "tags": {"addr:city": "Valtournenche", "name": "Vieille", "place": "hamlet"}}, {"type": "node", "id": 6154131906, "lat": 46.0656056, "lon": 7.7937518, "tags": {"name": "Eggenstadel", "place": "hamlet"}}, {"type": "node", "id": 6602483653, "lat": 46.1638923, "lon": 7.7980935}, {"type": "node", "id": 6606299905, "lat": 46.1730405, "lon": 7.7998562}, {"type": "node", "id": 6606299906, "lat": 46.1731952, "lon": 7.7998292}, {"type": "node", "id": 6611611348, "lat": 46.1855944, "lon": 7.7987059, "tags": {"alt_name": "Teli", "name": "Teeli", "place": "hamlet"}}, {"type": "node", "id": 6614868314, "lat": 46.1936345, "lon": 7.8027745, "tags": {"name": "Wintergadmen", "place": "hamlet"}}, {"type": "node", "id": 6614870446, "lat": 46.1971776, "lon": 7.8050462, "tags": {"name": "Lerchji", "place": "hamlet"}}, {"type": "node", "id": 6616731343, "lat": 46.1665454, "lon": 7.8042423, "tags": {"name": "Fl\u00fce", "place": "hamlet"}}, {"type": "node", "id": 6617197505, "lat": 46.1832004, "lon": 7.8122361}, {"type": "node", "id": 6617220254, "lat": 46.1981491, "lon": 7.8012374, "tags": {"name": "Egga", "place": "hamlet"}}, {"type": "node", "id": 6619065245, "lat": 46.1597121, "lon": 7.7956586}, {"type": "node", "id": 6627360493, "lat": 46.1751211, "lon": 7.8075993, "tags": {"name": "Hubulti", "place": "hamlet"}}, {"type": "node", "id": 6627363107, "lat": 46.1759592, "lon": 7.8097369, "tags": {"name": "St\u00fcdjini", "place": "hamlet"}}, {"type": "node", "id": 6628712464, "lat": 46.1657094, "lon": 7.7873628, "tags": {"name": "Medji", "place": "hamlet"}}, {"type": "node", "id": 6629670623, "lat": 46.1938943, "lon": 7.8012399, "tags": {"name": "Dili", "place": "hamlet"}}, {"type": "node", "id": 6629673111, "lat": 46.1969534, "lon": 7.8024393, "tags": {"name": "Biel", "place": "hamlet"}}, {"type": "node", "id": 6634006836, "lat": 46.1779312, "lon": 7.8066462, "tags": {"name": "Eye", "place": "hamlet"}}, {"type": "node", "id": 6634006842, "lat": 46.1886809, "lon": 7.8240238, "tags": {"name": "Rittinen", "place": "hamlet"}}, {"type": "node", "id": 6634006843, "lat": 46.1831774, "lon": 7.8128768, "tags": {"name": "Wichel", "place": "hamlet"}}, {"type": "node", "id": 6634006845, "lat": 46.1870094, "lon": 7.8110178, "tags": {"alt_name": "Lochmatte", "name": "Lochmatten", "place": "hamlet", "wikidata": "Q55502956"}}, {"type": "node", "id": 6634006849, "lat": 46.1625183, "lon": 7.7939862, "tags": {"name": "Schwiedernen", "place": "hamlet"}}, {"type": "node", "id": 6634006851, "lat": 46.1598279, "lon": 7.7961393, "tags": {"name": "Gehri", "place": "hamlet"}}, {"type": "node", "id": 6634006852, "lat": 46.1595363, "lon": 7.7975767, "tags": {"name": "Biffig", "place": "hamlet"}}, {"type": "node", "id": 6639607375, "lat": 46.1681453, "lon": 7.7978049, "tags": {"name": "Stahlen", "place": "hamlet"}}, {"type": "node", "id": 6643842800, "lat": 46.1277392, "lon": 7.7975639, "tags": {"name": "Geisstrift", "place": "hamlet"}}, {"type": "node", "id": 6653844271, "lat": 46.1185869, "lon": 7.7961271, "tags": {"name": "B\u00e4rgji", "place": "hamlet"}}, {"type": "node", "id": 6653874395, "lat": 46.1228895, "lon": 7.8015948, "tags": {"name": "H\u00f6\u00fcschbiel", "place": "hamlet"}}, {"type": "node", "id": 6690614124, "lat": 46.2069652, "lon": 7.8150284, "tags": {"name": "Grossberg", "place": "hamlet"}}, {"type": "node", "id": 6708039218, "lat": 46.209317, "lon": 7.8432452, "tags": {"name": "Bodo", "place": "hamlet"}}, {"type": "node", "id": 6779593387, "lat": 46.2412678, "lon": 7.8552054, "tags": {"name": "Bina", "place": "hamlet"}}, {"type": "node", "id": 6781008683, "lat": 46.1827414, "lon": 7.8254572, "tags": {"alt_name": "Ch\u00e4schermatte", "name": "K\u00e4schermatten", "place": "hamlet"}}, {"type": "node", "id": 6939917940, "lat": 46.183907, "lon": 7.8137743}, {"type": "node", "id": 6939917941, "lat": 46.1844069, "lon": 7.8136664}, {"type": "node", "id": 6939917942, "lat": 46.184677, "lon": 7.8132929}, {"type": "node", "id": 6939917943, "lat": 46.1846483, "lon": 7.8126787}, {"type": "node", "id": 6939917944, "lat": 46.1841369, "lon": 7.8121392}, {"type": "node", "id": 6939917945, "lat": 46.1835105, "lon": 7.8118238}, {"type": "node", "id": 6939917946, "lat": 46.1825796, "lon": 7.8117408}, {"type": "node", "id": 6939917947, "lat": 46.1825911, "lon": 7.8126704}, {"type": "node", "id": 7077810997, "lat": 46.1698124, "lon": 7.7981112}, {"type": "node", "id": 7077810998, "lat": 46.1690509, "lon": 7.7967012}, {"type": "node", "id": 7077810999, "lat": 46.1680231, "lon": 7.7964247}, {"type": "node", "id": 7077811000, "lat": 46.1677007, "lon": 7.7973624}, {"type": "node", "id": 7077811001, "lat": 46.1670466, "lon": 7.7970385}, {"type": "node", "id": 7077811002, "lat": 46.166272, "lon": 7.7969913}, {"type": "node", "id": 7077811003, "lat": 46.1658561, "lon": 7.7969846}, {"type": "node", "id": 7077811004, "lat": 46.1658048, "lon": 7.7977199}, {"type": "node", "id": 7077811005, "lat": 46.1666597, "lon": 7.7989747}, {"type": "node", "id": 7077811006, "lat": 46.1681268, "lon": 7.7999663}, {"type": "node", "id": 7077811007, "lat": 46.1689724, "lon": 7.79971}, {"type": "node", "id": 7077811008, "lat": 46.1694711, "lon": 7.7990016}, {"type": "node", "id": 7077813029, "lat": 46.17779, "lon": 7.8123871}, {"type": "node", "id": 7077813030, "lat": 46.177251, "lon": 7.8108907}, {"type": "node", "id": 7077813031, "lat": 46.1762508, "lon": 7.8105275}, {"type": "node", "id": 7077813032, "lat": 46.1754632, "lon": 7.8114085}, {"type": "node", "id": 7077813033, "lat": 46.1755641, "lon": 7.8123662}, {"type": "node", "id": 7077813034, "lat": 46.175381, "lon": 7.8145445}, {"type": "node", "id": 7077813035, "lat": 46.1774959, "lon": 7.8145692}, {"type": "node", "id": 7077813036, "lat": 46.1779232, "lon": 7.8133372}, {"type": "node", "id": 7077814103, "lat": 46.1593472, "lon": 7.7980134}, {"type": "node", "id": 7077814104, "lat": 46.1618606, "lon": 7.798243}, {"type": "node", "id": 7077814224, "lat": 46.1655962, "lon": 7.7951069}, {"type": "node", "id": 7077814225, "lat": 46.1658654, "lon": 7.7962994}, {"type": "node", "id": 7077814226, "lat": 46.1638785, "lon": 7.79565}, {"type": "node", "id": 7077814227, "lat": 46.1632104, "lon": 7.7951912}, {"type": "node", "id": 7077814228, "lat": 46.1622452, "lon": 7.7945301}, {"type": "node", "id": 7077814229, "lat": 46.1618995, "lon": 7.7939162}, {"type": "node", "id": 7077814230, "lat": 46.1618901, "lon": 7.7932619}, {"type": "node", "id": 7077814231, "lat": 46.1623247, "lon": 7.7932821}, {"type": "node", "id": 7077814232, "lat": 46.162619, "lon": 7.7931202}, {"type": "node", "id": 7077814233, "lat": 46.1641514, "lon": 7.7943345}, {"type": "node", "id": 7077814234, "lat": 46.1642869, "lon": 7.793788}, {"type": "node", "id": 7077814235, "lat": 46.1653101, "lon": 7.7946111}, {"type": "node", "id": 7077817743, "lat": 46.161647, "lon": 7.7968103}, {"type": "node", "id": 7077817744, "lat": 46.1613853, "lon": 7.7975254}, {"type": "node", "id": 7077817745, "lat": 46.1615915, "lon": 7.7978365}, {"type": "node", "id": 7077817746, "lat": 46.1620098, "lon": 7.7984916}, {"type": "node", "id": 7077817747, "lat": 46.162502, "lon": 7.7989825}, {"type": "node", "id": 7077817748, "lat": 46.1630767, "lon": 7.79905}, {"type": "node", "id": 7077817749, "lat": 46.1634038, "lon": 7.7989758}, {"type": "node", "id": 7077817750, "lat": 46.1634412, "lon": 7.7984293}, {"type": "node", "id": 7077817751, "lat": 46.1624319, "lon": 7.7973904}, {"type": "node", "id": 7077817752, "lat": 46.1622326, "lon": 7.7987482}, {"type": "node", "id": 7077819050, "lat": 46.1651621, "lon": 7.7982265}, {"type": "node", "id": 7077819051, "lat": 46.1651273, "lon": 7.799846}, {"type": "node", "id": 7077819052, "lat": 46.1633223, "lon": 7.7972732}, {"type": "node", "id": 7077819053, "lat": 46.1637601, "lon": 7.7966744}, {"type": "node", "id": 7077819054, "lat": 46.1645513, "lon": 7.7968518}, {"type": "node", "id": 7077819055, "lat": 46.1650889, "lon": 7.796996}, {"type": "node", "id": 7077819056, "lat": 46.165203, "lon": 7.7975535}, {"type": "node", "id": 7077819057, "lat": 46.1652171, "lon": 7.7979601}, {"type": "node", "id": 7077820828, "lat": 46.1828351, "lon": 7.8128751}, {"type": "node", "id": 7484693587, "lat": 46.1656029, "lon": 7.795445}, {"type": "node", "id": 7484693588, "lat": 46.1657786, "lon": 7.7956466}, {"type": "node", "id": 7484705612, "lat": 46.1655454, "lon": 7.7950189}, {"type": "node", "id": 7484705613, "lat": 46.1715467, "lon": 7.7997088}, {"type": "node", "id": 7484705614, "lat": 46.1711111, "lon": 7.7992931}, {"type": "node", "id": 7484705615, "lat": 46.1706415, "lon": 7.7993314}, {"type": "node", "id": 7484705616, "lat": 46.1704824, "lon": 7.7982759}, {"type": "node", "id": 7484705617, "lat": 46.1706793, "lon": 7.7980024}, {"type": "node", "id": 7484705618, "lat": 46.1714066, "lon": 7.7974992}, {"type": "node", "id": 7484705619, "lat": 46.1716452, "lon": 7.7974226}, {"type": "node", "id": 7484705620, "lat": 46.1719633, "lon": 7.797357}, {"type": "node", "id": 7484705621, "lat": 46.1724027, "lon": 7.7976578}, {"type": "node", "id": 7484705622, "lat": 46.1727242, "lon": 7.7980243}, {"type": "node", "id": 7484705623, "lat": 46.1729931, "lon": 7.7982594}, {"type": "node", "id": 7484705624, "lat": 46.1732847, "lon": 7.7986915}, {"type": "node", "id": 7484705625, "lat": 46.1736369, "lon": 7.7990033}, {"type": "node", "id": 7484705626, "lat": 46.1734248, "lon": 7.7995666}, {"type": "node", "id": 7484705627, "lat": 46.1732582, "lon": 7.7998182}, {"type": "node", "id": 7484705628, "lat": 46.1729135, "lon": 7.7998784}, {"type": "node", "id": 7484705629, "lat": 46.1723682, "lon": 7.7996213}, {"type": "node", "id": 7484705630, "lat": 46.171925, "lon": 7.7996924}, {"type": "node", "id": 7484705631, "lat": 46.1717054, "lon": 7.7998838}, {"type": "node", "id": 7484721477, "lat": 46.1858178, "lon": 7.8158432}, {"type": "node", "id": 7484721478, "lat": 46.1856209, "lon": 7.8157227}, {"type": "node", "id": 7484721479, "lat": 46.1855942, "lon": 7.8152311}, {"type": "node", "id": 7484721480, "lat": 46.1861281, "lon": 7.8148792}, {"type": "node", "id": 7484721481, "lat": 46.1864351, "lon": 7.8146045}, {"type": "node", "id": 7484721482, "lat": 46.186642, "lon": 7.8144262}, {"type": "node", "id": 7484721483, "lat": 46.1868355, "lon": 7.8143635}, {"type": "node", "id": 7484721484, "lat": 46.1870157, "lon": 7.8146816}, {"type": "node", "id": 7484724995, "lat": 46.1902864, "lon": 7.8187181}, {"type": "node", "id": 7484724996, "lat": 46.1897399, "lon": 7.8195345}, {"type": "node", "id": 7484724997, "lat": 46.1891747, "lon": 7.8191398}, {"type": "node", "id": 7484724998, "lat": 46.1891064, "lon": 7.8185656}, {"type": "node", "id": 7484724999, "lat": 46.1894852, "lon": 7.8181888}, {"type": "node", "id": 7484725000, "lat": 46.1898082, "lon": 7.8184131}, {"type": "node", "id": 7484725001, "lat": 46.1900628, "lon": 7.8183413}, {"type": "node", "id": 7484725285, "lat": 46.1871225, "lon": 7.8152793}, {"type": "node", "id": 7484725286, "lat": 46.1870224, "lon": 7.8154528}, {"type": "node", "id": 7484725287, "lat": 46.1865886, "lon": 7.8156215}, {"type": "node", "id": 7484725288, "lat": 46.1865586, "lon": 7.815901}, {"type": "node", "id": 7484725289, "lat": 46.186048, "lon": 7.8159106}, {"type": "node", "id": 7484727308, "lat": 46.1860279, "lon": 7.8197034}, {"type": "node", "id": 7484727309, "lat": 46.1853819, "lon": 7.819518}, {"type": "node", "id": 7484727310, "lat": 46.185061, "lon": 7.8190422}, {"type": "node", "id": 7484727311, "lat": 46.1852963, "lon": 7.8183254}, {"type": "node", "id": 7484727312, "lat": 46.1857712, "lon": 7.8178558}, {"type": "node", "id": 7484727313, "lat": 46.1862504, "lon": 7.8176333}, {"type": "node", "id": 7484727314, "lat": 46.1866482, "lon": 7.8176148}, {"type": "node", "id": 7484727315, "lat": 46.1872087, "lon": 7.8176271}, {"type": "node", "id": 7484727316, "lat": 46.1874384, "lon": 7.8174232}, {"type": "node", "id": 7484727317, "lat": 46.1877464, "lon": 7.8174665}, {"type": "node", "id": 7484727318, "lat": 46.1879261, "lon": 7.8176271}, {"type": "node", "id": 7484727319, "lat": 46.1881913, "lon": 7.8179237}, {"type": "node", "id": 7484727320, "lat": 46.1878576, "lon": 7.8186344}, {"type": "node", "id": 7484727321, "lat": 46.1872116, "lon": 7.8190855}, {"type": "node", "id": 7484727322, "lat": 46.1867496, "lon": 7.8195119}, {"type": "node", "id": 7484782000, "lat": 46.1614458, "lon": 7.8021475, "tags": {"name": "Balmu", "place": "hamlet"}}, {"type": "node", "id": 7519478830, "lat": 46.1653256, "lon": 7.7990684}, {"type": "node", "id": 7519478831, "lat": 46.1655698, "lon": 7.7995131}, {"type": "node", "id": 7519503696, "lat": 46.1654119, "lon": 7.7997477}, {"type": "node", "id": 7519503697, "lat": 46.1649158, "lon": 7.7996506}, {"type": "node", "id": 7547195647, "lat": 46.2488212, "lon": 7.9117441, "tags": {"name": "Egga", "place": "hamlet"}}, {"type": "node", "id": 7574808745, "lat": 46.1850556, "lon": 7.8167568}, {"type": "node", "id": 7574808746, "lat": 46.1847112, "lon": 7.816248}, {"type": "node", "id": 7574808747, "lat": 46.1844842, "lon": 7.8161915}, {"type": "node", "id": 7574808748, "lat": 46.1842259, "lon": 7.8164515}, {"type": "node", "id": 7574808749, "lat": 46.184218, "lon": 7.8171751}, {"type": "node", "id": 7574808750, "lat": 46.1843981, "lon": 7.8173334}, {"type": "node", "id": 7574808751, "lat": 46.1848756, "lon": 7.8173674}, {"type": "node", "id": 7782097062, "lat": 46.1477025, "lon": 7.6221224, "tags": {"name": "Vernec", "place": "hamlet"}}, {"type": "node", "id": 7858419184, "lat": 46.131908, "lon": 7.7848394, "tags": {"name": "R\u00e4ckholder", "place": "hamlet"}}, {"type": "node", "id": 7858422059, "lat": 46.1828784, "lon": 7.8285896, "tags": {"name": "Erbji", "place": "hamlet"}}, {"type": "node", "id": 7858427822, "lat": 46.184097, "lon": 7.8059264, "tags": {"name": "Esch", "place": "hamlet"}}, {"type": "node", "id": 7858434760, "lat": 46.1954904, "lon": 7.7993203, "tags": {"name": "Jungen", "place": "hamlet"}}, {"type": "node", "id": 7858461388, "lat": 46.1729727, "lon": 7.7879899, "tags": {"name": "Riedji", "place": "hamlet"}}, {"type": "node", "id": 9067865342, "lat": 46.1072797, "lon": 7.7902049, "tags": {"name": "Gere", "place": "hamlet"}}, {"type": "node", "id": 9376040873, "lat": 46.2544457, "lon": 7.5679042, "tags": {"name": "Fiez", "place": "hamlet"}}, {"type": "node", "id": 9376040901, "lat": 46.2451813, "lon": 7.5729514, "tags": {"name": "La Tsany\u00e8ya", "place": "hamlet"}}, {"type": "node", "id": 9397350593, "lat": 45.9105272, "lon": 7.4970629, "tags": {"name": "Bionaz", "place": "village"}}, {"type": "node", "id": 9400524966, "lat": 46.2118046, "lon": 7.8163781, "tags": {"name": "Zum Chriz", "place": "hamlet"}}, {"type": "node", "id": 9502362483, "lat": 45.9912409, "lon": 7.7099991, "tags": {"ele": "2588", "name": "Schwarzsee", "place": "hamlet"}}, {"type": "node", "id": 9750086356, "lat": 46.1713785, "lon": 7.3973407, "tags": {"name": "Ayer", "place": "hamlet"}}, {"type": "node", "id": 9753014685, "lat": 46.1509404, "lon": 7.4701263, "tags": {"name": "La Crettaz", "place": "hamlet"}}, {"type": "node", "id": 9909273762, "lat": 45.9515823, "lon": 7.631515, "tags": {"ele": "2487", "name": "Crot de Labies", "place": "hamlet"}}, {"type": "node", "id": 10704046829, "lat": 46.1945134, "lon": 7.8159247, "tags": {"name": "S\u00e4lli", "place": "hamlet"}}, {"type": "node", "id": 10760619578, "lat": 46.22967, "lon": 7.8834061, "tags": {"name": "Zer Tanne", "place": "hamlet"}}, {"type": "node", "id": 11452164379, "lat": 46.1712032, "lon": 7.4626926, "tags": {"name": "Pravouarbot", "place": "hamlet"}}, {"type": "node", "id": 12009256124, "lat": 46.1926989, "lon": 7.8004894, "tags": {"name": "Gaffine", "place": "hamlet"}}, {"type": "node", "id": 12045065194, "lat": 46.1755343, "lon": 7.9006571, "tags": {"alt_name": "Schweiben", "name": "Schweibu", "place": "hamlet"}}, {"type": "node", "id": 12045108848, "lat": 46.1885454, "lon": 7.902723, "tags": {"name": "Ahorn", "place": "hamlet"}}, {"type": "node", "id": 12045115110, "lat": 46.1790777, "lon": 7.9072048, "tags": {"name": "Bodenbr\u00fccke", "place": "hamlet"}}, {"type": "node", "id": 12047160235, "lat": 46.1472353, "lon": 7.7930013, "tags": {"name": "Mattsand", "place": "hamlet"}}, {"type": "node", "id": 12047160240, "lat": 46.1271272, "lon": 7.788602, "tags": {"name": "Zenackern", "place": "hamlet"}}, {"type": "node", "id": 12047160242, "lat": 46.1223245, "lon": 7.7897811, "tags": {"alt_name": "Breitmattu", "name": "Breitmatten", "place": "hamlet"}}, {"type": "node", "id": 12487337620, "lat": 46.175725, "lon": 7.8177396}, {"type": "node", "id": 12487337621, "lat": 46.173695, "lon": 7.817492}, {"type": "node", "id": 12487337622, "lat": 46.174177, "lon": 7.818279}, {"type": "node", "id": 12487337623, "lat": 46.1754901, "lon": 7.8152582}, {"type": "node", "id": 12487337624, "lat": 46.1749713, "lon": 7.8162149}, {"type": "node", "id": 12487337625, "lat": 46.173936, "lon": 7.8178855}, {"type": "node", "id": 12487337627, "lat": 46.1749059, "lon": 7.8131977}, {"type": "node", "id": 12487337628, "lat": 46.1770527, "lon": 7.8154362}, {"type": "way", "id": 140579441, "nodes": [1539960857, 1539960874, 1539960957, 1539960989, 1539960891, 1539960875, 1539961028, 7077814103, 1539961060, 1539961077, 1539961019, 1539960994, 1539960944, 1539961035, 1539961054, 1539960982, 1539961012, 1539961063, 1539960869, 1539961062, 364691620, 364691621, 6619065245, 1016532278, 1016532223, 1384833234, 1384833231, 1384833246, 1539960857], "tags": {"landuse": "residential", "place": "hamlet"}}, {"type": "way", "id": 741318232, "nodes": [6939917940, 6939917941, 6939917942, 6939917943, 6939917944, 6939917945, 6617197505, 6939917946, 1312041795, 6939917947, 7077820828, 6939917940], "tags": {"name": "Wichel", "place": "hamlet"}}, {"type": "way", "id": 757861546, "nodes": [7077810997, 7077810998, 7077810999, 7077811000, 7077811001, 7077811002, 7077811003, 7077811004, 7077811005, 7077811006, 7077811007, 7077811008, 7077810997], "tags": {"name": "Stahlen", "place": "hamlet"}}, {"type": "way", "id": 757861696, "nodes": [7077819050, 7519478830, 7519478831, 7519503696, 7077819051, 7519503697, 6602483653, 7077819052, 7077819053, 7077819054, 7077819055, 7077819056, 7077819057, 7077819050], "tags": {"name": "Balmatten", "place": "hamlet"}}, {"type": "way", "id": 757861880, "nodes": [7077814224, 7484693587, 7484693588, 7077814225, 7077814226, 7077814227, 7077814228, 7077814229, 7077814230, 7077814231, 7077814232, 7077814233, 7077814234, 7077814235, 7484705612, 7077814224], "tags": {"name": "Schwiedernen", "place": "hamlet"}}, {"type": "way", "id": 757862010, "nodes": [7077817743, 7077817744, 7077817745, 7077814104, 7077817746, 7077817752, 7077817747, 7077817748, 7077817749, 7077817750, 7077817751, 7077817743], "tags": {"name": "Balacker", "place": "hamlet"}}, {"type": "way", "id": 757862365, "nodes": [7077813029, 7077813030, 7077813031, 7077813032, 7077813033, 12487337627, 7077813034, 12487337623, 12487337624, 12487337621, 12487337625, 12487337622, 12487337620, 12487337628, 7077813035, 7077813036, 7077813029], "tags": {"name": "Tennjen", "place": "hamlet"}}, {"type": "way", "id": 800315139, "nodes": [7484705613, 7484705614, 7484705615, 7484705616, 7484705617, 7484705618, 7484705619, 7484705620, 7484705621, 7484705622, 7484705623, 7484705624, 7484705625, 7484705626, 7484705627, 6606299906, 6606299905, 7484705628, 7484705629, 7484705630, 7484705631, 7484705613], "tags": {"name": "Birchmatten", "place": "hamlet"}}, {"type": "way", "id": 800317131, "nodes": [7484721477, 7484721478, 7484721479, 7484721480, 7484721481, 7484721482, 7484721483, 7484721484, 7484725285, 7484725286, 7484725287, 7484725288, 7484725289, 7484721477], "tags": {"alt_name": "Roossen", "name": "Rossen", "place": "hamlet"}}, {"type": "way", "id": 800317415, "nodes": [7484727308, 7484727309, 7484727310, 7484727311, 7484727312, 7484727313, 7484727314, 7484727315, 7484727316, 7484727317, 7484727318, 7484727319, 7484727320, 7484727321, 7484727322, 7484727308], "tags": {"name": "Bodmen", "place": "hamlet"}}, {"type": "way", "id": 800318069, "nodes": [7484724995, 7484724996, 7484724997, 7484724998, 7484724999, 7484725000, 7484725001, 7484724995], "tags": {"name": "Hintere Bodmen", "place": "hamlet"}}, {"type": "way", "id": 810193623, "nodes": [7574808745, 7574808746, 7574808747, 7574808748, 7574808749, 7574808750, 7574808751, 7574808745], "tags": {"name": "Zermetjen", "place": "hamlet"}}]}